pykarma
