Metadata-Version: 1.0
Name: pykarma
Version: 1.2
Summary: A python API for Karma Decay
Home-page: http://github.com/samj1912/pykarma
Author: Sambhav Kothari
Author-email: sambhavs.email@gmail.com
License: MIT
Platform: UNKNOWN
